[{"name": "aten::conv2d", "ph": "X", "ts": 20.608, "dur": 125.161, "tid": 1, "pid": "CPU functions", "args": {}}, {"name": "aten::conv2d", "ph": "s", "ts": 20.608, "tid": 1, "pid": "CPU functions", "id": 0, "cat": "cpu_to_cuda", "args": {}}, {"name": "aten::conv2d", "ph": "f", "ts": 21.270999206542967, "tid": 0, "pid": "CUDA functions", "id": 0, "cat": "cpu_to_cuda", "args": {}}, {"name": "aten::conv2d", "ph": "X", "ts": 21.270999206542967, "dur": 124.9280014038086, "tid": 0, "pid": "CUDA functions", "args": {}}, {"name": "aten::convolution", "ph": "X", "ts": 24.383, "dur": 119.623, "tid": 1, "pid": "CPU functions", "args": {}}, {"name": "aten::convolution", "ph": "s", "ts": 24.383, "tid": 1, "pid": "CPU functions", "id": 1, "cat": "cpu_to_cuda", "args": {}}, {"name": "aten::convolution", "ph": "f", "ts": 24.53499914550781, "tid": 0, "pid": "CUDA functions", "id": 1, "cat": "cpu_to_cuda", "args": {}}, {"name": "aten::convolution", "ph": "X", "ts": 24.53499914550781, "dur": 119.61599731445312, "tid": 0, "pid": "CUDA functions", "args": {}}, {"name": "aten::_convolution", "ph": "X", "ts": 27.491, "dur": 114.55999999999999, "tid": 1, "pid": "CPU functions", "args": {}}, {"name": "aten::_convolution", "ph": "s", "ts": 27.491, "tid": 1, "pid": "CPU functions", "id": 2, "cat": "cpu_to_cuda", "args": {}}, {"name": "aten::_convolution", "ph": "f", "ts": 28.439000381469725, "tid": 0, "pid": "CUDA functions", "id": 2, "cat": "cpu_to_cuda", "args": {}}, {"name": "aten::_convolution", "ph": "X", "ts": 28.439000381469725, "dur": 114.04799461364746, "tid": 0, "pid": "CUDA functions", "args": {}}, {"name": "aten::contiguous", "ph": "X", "ts": 34.304, "dur": 2.1679999999999993, "tid": 1, "pid": "CPU functions", "args": {}}, {"name": "aten::contiguous", "ph": "s", "ts": 34.304, "tid": 1, "pid": "CPU functions", "id": 3, "cat": "cpu_to_cuda", "args": {}}, {"name": "aten::contiguous", "ph": "f", "ts": 34.58299948120117, "tid": 0, "pid": "CUDA functions", "id": 3, "cat": "cpu_to_cuda", "args": {}}, {"name": "aten::contiguous", "ph": "X", "ts": 34.58299948120117, "dur": 2.0480003356933594, "tid": 0, "pid": "CUDA functions", "args": {}}, {"name": "aten::cudnn_convolution", "ph": "X", "ts": 39.044, "dur": 65.554, "tid": 1, "pid": "CPU functions", "args": {}}, {"name": "aten::cudnn_convolution", "ph": "s", "ts": 39.044, "tid": 1, "pid": "CPU functions", "id": 4, "cat": "cpu_to_cuda", "args": {}}, {"name": "aten::cudnn_convolution", "ph": "f", "ts": 39.702998413085936, "tid": 0, "pid": "CUDA functions", "id": 4, "cat": "cpu_to_cuda", "args": {}}, {"name": "aten::cudnn_convolution", "ph": "X", "ts": 39.702998413085936, "dur": 74.75200653076172, "tid": 0, "pid": "CUDA functions", "args": {}}, {"name": "aten::empty", "ph": "X", "ts": 49.964, "dur": 5.18, "tid": 1, "pid": "CPU functions", "args": {}}, {"name": "aten::contiguous", "ph": "X", "ts": 57.401, "dur": 1.7629999999999981, "tid": 1, "pid": "CPU functions", "args": {}}, {"name": "aten::contiguous", "ph": "s", "ts": 57.401, "tid": 1, "pid": "CPU functions", "id": 5, "cat": "cpu_to_cuda", "args": {}}, {"name": "aten::contiguous", "ph": "f", "ts": 57.526999725341796, "tid": 0, "pid": "CUDA functions", "id": 5, "cat": "cpu_to_cuda", "args": {}}, {"name": "aten::contiguous", "ph": "X", "ts": 57.526999725341796, "dur": 1.66400146484375, "tid": 0, "pid": "CUDA functions", "args": {}}, {"name": "aten::resize_", "ph": "X", "ts": 61.18, "dur": 0.6480000000000032, "tid": 1, "pid": "CPU functions", "args": {}}, {"name": "aten::contiguous", "ph": "X", "ts": 62.726, "dur": 1.7270000000000039, "tid": 1, "pid": "CPU functions", "args": {}}, {"name": "aten::contiguous", "ph": "s", "ts": 62.726, "tid": 1, "pid": "CPU functions", "id": 6, "cat": "cpu_to_cuda", "args": {}}, {"name": "aten::contiguous", "ph": "f", "ts": 63.255000366210936, "tid": 0, "pid": "CUDA functions", "id": 6, "cat": "cpu_to_cuda", "args": {}}, {"name": "aten::contiguous", "ph": "X", "ts": 63.255000366210936, "dur": 1.0240020751953125, "tid": 0, "pid": "CUDA functions", "args": {}}, {"name": "aten::resize_", "ph": "X", "ts": 65.742, "dur": 0.3579999999999899, "tid": 1, "pid": "CPU functions", "args": {}}, {"name": "aten::stride", "ph": "X", "ts": 68.771, "dur": 0.29999999999999716, "tid": 1, "pid": "CPU functions", "args": {}}, {"name": "aten::stride", "ph": "X", "ts": 69.633, "dur": 0.21800000000000352, "tid": 1, "pid": "CPU functions", "args": {}}, {"name": "aten::stride", "ph": "X", "ts": 70.331, "dur": 0.21599999999999397, "tid": 1, "pid": "CPU functions", "args": {}}, {"name": "aten::stride", "ph": "X", "ts": 71.021, "dur": 0.21099999999999852, "tid": 1, "pid": "CPU functions", "args": {}}, {"name": "aten::empty", "ph": "X", "ts": 74.811, "dur": 0.8859999999999957, "tid": 1, "pid": "CPU functions", "args": {}}, {"name": "aten::reshape", "ph": "X", "ts": 107.993, "dur": 11.704000000000008, "tid": 1, "pid": "CPU functions", "args": {}}, {"name": "aten::reshape", "ph": "s", "ts": 107.993, "tid": 1, "pid": "CPU functions", "id": 7, "cat": "cpu_to_cuda", "args": {}}, {"name": "aten::reshape", "ph": "f", "ts": 115.47899938964844, "tid": 0, "pid": "CUDA functions", "id": 7, "cat": "cpu_to_cuda", "args": {}}, {"name": "aten::reshape", "ph": "X", "ts": 115.47899938964844, "dur": 5.120002746582031, "tid": 0, "pid": "CUDA functions", "args": {}}, {"name": "aten::view", "ph": "X", "ts": 111.012, "dur": 7.221999999999994, "tid": 1, "pid": "CPU functions", "args": {}}, {"name": "aten::add_", "ph": "X", "ts": 122.479, "dur": 17.12400000000001, "tid": 1, "pid": "CPU functions", "args": {}}, {"name": "aten::add_", "ph": "s", "ts": 122.479, "tid": 1, "pid": "CPU functions", "id": 8, "cat": "cpu_to_cuda", "args": {}}, {"name": "aten::add_", "ph": "f", "ts": 122.64699865722656, "tid": 0, "pid": "CUDA functions", "id": 8, "cat": "cpu_to_cuda", "args": {}}, {"name": "aten::add_", "ph": "X", "ts": 122.64699865722656, "dur": 17.407989501953125, "tid": 0, "pid": "CUDA functions", "args": {}}, {"name": "aten::relu", "ph": "X", "ts": 155.728, "dur": 26.308999999999997, "tid": 1, "pid": "CPU functions", "args": {}}, {"name": "aten::relu", "ph": "s", "ts": 155.728, "tid": 1, "pid": "CPU functions", "id": 9, "cat": "cpu_to_cuda", "args": {}}, {"name": "aten::relu", "ph": "f", "ts": 156.43900610351562, "tid": 0, "pid": "CUDA functions", "id": 9, "cat": "cpu_to_cuda", "args": {}}, {"name": "aten::relu", "ph": "X", "ts": 156.43900610351562, "dur": 25.69598388671875, "tid": 0, "pid": "CUDA functions", "args": {}}, {"name": "aten::threshold", "ph": "X", "ts": 162.966, "dur": 13.945999999999998, "tid": 1, "pid": "CPU functions", "args": {}}, {"name": "aten::threshold", "ph": "s", "ts": 162.966, "tid": 1, "pid": "CPU functions", "id": 10, "cat": "cpu_to_cuda", "args": {}}, {"name": "aten::threshold", "ph": "f", "ts": 162.64699865722656, "tid": 0, "pid": "CUDA functions", "id": 10, "cat": "cpu_to_cuda", "args": {}}, {"name": "aten::threshold", "ph": "X", "ts": 162.64699865722656, "dur": 15.552001953125, "tid": 0, "pid": "CUDA functions", "args": {}}, {"name": "aten::empty", "ph": "X", "ts": 166.903, "dur": 4.349000000000018, "tid": 1, "pid": "CPU functions", "args": {}}, {"name": "aten::max_pool2d", "ph": "X", "ts": 195.457, "dur": 40.48600000000002, "tid": 1, "pid": "CPU functions", "args": {}}, {"name": "aten::max_pool2d", "ph": "s", "ts": 195.457, "tid": 1, "pid": "CPU functions", "id": 11, "cat": "cpu_to_cuda", "args": {}}, {"name": "aten::max_pool2d", "ph": "f", "ts": 195.60700537109375, "tid": 0, "pid": "CUDA functions", "id": 11, "cat": "cpu_to_cuda", "args": {}}, {"name": "aten::max_pool2d", "ph": "X", "ts": 195.60700537109375, "dur": 39.67999267578125, "tid": 0, "pid": "CUDA functions", "args": {}}, {"name": "aten::max_pool2d_with_indices", "ph": "X", "ts": 198.381, "dur": 35.74000000000001, "tid": 1, "pid": "CPU functions", "args": {}}, {"name": "aten::max_pool2d_with_indices", "ph": "s", "ts": 198.381, "tid": 1, "pid": "CPU functions", "id": 12, "cat": "cpu_to_cuda", "args": {}}, {"name": "aten::max_pool2d_with_indices", "ph": "f", "ts": 198.42301489257812, "tid": 0, "pid": "CUDA functions", "id": 12, "cat": "cpu_to_cuda", "args": {}}, {"name": "aten::max_pool2d_with_indices", "ph": "X", "ts": 198.42301489257812, "dur": 35.87199401855469, "tid": 0, "pid": "CUDA functions", "args": {}}, {"name": "aten::empty", "ph": "X", "ts": 205.236, "dur": 1.0250000000000057, "tid": 1, "pid": "CPU functions", "args": {}}, {"name": "aten::empty", "ph": "X", "ts": 206.931, "dur": 0.6769999999999925, "tid": 1, "pid": "CPU functions", "args": {}}, {"name": "aten::contiguous", "ph": "X", "ts": 209.953, "dur": 2.0320000000000107, "tid": 1, "pid": "CPU functions", "args": {}}, {"name": "aten::contiguous", "ph": "s", "ts": 209.953, "tid": 1, "pid": "CPU functions", "id": 13, "cat": "cpu_to_cuda", "args": {}}, {"name": "aten::contiguous", "ph": "f", "ts": 210.7109940185547, "tid": 0, "pid": "CUDA functions", "id": 13, "cat": "cpu_to_cuda", "args": {}}, {"name": "aten::contiguous", "ph": "X", "ts": 210.7109940185547, "dur": 1.024017333984375, "tid": 0, "pid": "CUDA functions", "args": {}}, {"name": "aten::stride", "ph": "X", "ts": 213.396, "dur": 0.31100000000000705, "tid": 1, "pid": "CPU functions", "args": {}}, {"name": "aten::stride", "ph": "X", "ts": 214.044, "dur": 0.214999999999975, "tid": 1, "pid": "CPU functions", "args": {}}, {"name": "aten::stride", "ph": "X", "ts": 214.585, "dur": 0.2150000000000034, "tid": 1, "pid": "CPU functions", "args": {}}, {"name": "aten::stride", "ph": "X", "ts": 215.119, "dur": 0.21299999999999386, "tid": 1, "pid": "CPU functions", "args": {}}, {"name": "aten::resize_", "ph": "X", "ts": 215.854, "dur": 4.006, "tid": 1, "pid": "CPU functions", "args": {}}, {"name": "aten::resize_", "ph": "X", "ts": 220.279, "dur": 2.819999999999993, "tid": 1, "pid": "CPU functions", "args": {}}, {"name": "aten::conv2d", "ph": "X", "ts": 251.997, "dur": 103.62799999999999, "tid": 1, "pid": "CPU functions", "args": {}}, {"name": "aten::conv2d", "ph": "s", "ts": 251.997, "tid": 1, "pid": "CPU functions", "id": 14, "cat": "cpu_to_cuda", "args": {}}, {"name": "aten::conv2d", "ph": "f", "ts": 252.6950028076172, "tid": 0, "pid": "CUDA functions", "id": 14, "cat": "cpu_to_cuda", "args": {}}, {"name": "aten::conv2d", "ph": "X", "ts": 252.6950028076172, "dur": 103.42399597167969, "tid": 0, "pid": "CUDA functions", "args": {}}, {"name": "aten::convolution", "ph": "X", "ts": 255.701, "dur": 97.64099999999999, "tid": 1, "pid": "CPU functions", "args": {}}, {"name": "aten::convolution", "ph": "s", "ts": 255.701, "tid": 1, "pid": "CPU functions", "id": 15, "cat": "cpu_to_cuda", "args": {}}, {"name": "aten::convolution", "ph": "f", "ts": 255.95902563476562, "tid": 0, "pid": "CUDA functions", "id": 15, "cat": "cpu_to_cuda", "args": {}}, {"name": "aten::convolution", "ph": "X", "ts": 255.95902563476562, "dur": 97.08798217773438, "tid": 0, "pid": "CUDA functions", "args": {}}, {"name": "aten::_convolution", "ph": "X", "ts": 259.468, "dur": 92.14799999999997, "tid": 1, "pid": "CPU functions", "args": {}}, {"name": "aten::_convolution", "ph": "s", "ts": 259.468, "tid": 1, "pid": "CPU functions", "id": 16, "cat": "cpu_to_cuda", "args": {}}, {"name": "aten::_convolution", "ph": "f", "ts": 259.9270126953125, "tid": 0, "pid": "CUDA functions", "id": 16, "cat": "cpu_to_cuda", "args": {}}, {"name": "aten::_convolution", "ph": "X", "ts": 259.9270126953125, "dur": 92.09600830078125, "tid": 0, "pid": "CUDA functions", "args": {}}, {"name": "aten::contiguous", "ph": "X", "ts": 267.214, "dur": 2.7320000000000277, "tid": 1, "pid": "CPU functions", "args": {}}, {"name": "aten::contiguous", "ph": "s", "ts": 267.214, "tid": 1, "pid": "CPU functions", "id": 17, "cat": "cpu_to_cuda", "args": {}}, {"name": "aten::contiguous", "ph": "f", "ts": 268.05500341796875, "tid": 0, "pid": "CUDA functions", "id": 17, "cat": "cpu_to_cuda", "args": {}}, {"name": "aten::contiguous", "ph": "X", "ts": 268.05500341796875, "dur": 2.0479736328125, "tid": 0, "pid": "CUDA functions", "args": {}}, {"name": "aten::cudnn_convolution", "ph": "X", "ts": 271.948, "dur": 51.721000000000004, "tid": 1, "pid": "CPU functions", "args": {}}, {"name": "aten::cudnn_convolution", "ph": "s", "ts": 271.948, "tid": 1, "pid": "CPU functions", "id": 18, "cat": "cpu_to_cuda", "args": {}}, {"name": "aten::cudnn_convolution", "ph": "f", "ts": 272.15101171875, "tid": 0, "pid": "CUDA functions", "id": 18, "cat": "cpu_to_cuda", "args": {}}, {"name": "aten::cudnn_convolution", "ph": "X", "ts": 272.15101171875, "dur": 55.295989990234375, "tid": 0, "pid": "CUDA functions", "args": {}}, {"name": "aten::empty", "ph": "X", "ts": 280.496, "dur": 3.8799999999999955, "tid": 1, "pid": "CPU functions", "args": {}}, {"name": "aten::contiguous", "ph": "X", "ts": 286.084, "dur": 1.6370000000000005, "tid": 1, "pid": "CPU functions", "args": {}}, {"name": "aten::contiguous", "ph": "s", "ts": 286.084, "tid": 1, "pid": "CPU functions", "id": 19, "cat": "cpu_to_cuda", "args": {}}, {"name": "aten::contiguous", "ph": "f", "ts": 286.4869797363281, "tid": 0, "pid": "CUDA functions", "id": 19, "cat": "cpu_to_cuda", "args": {}}, {"name": "aten::contiguous", "ph": "X", "ts": 286.4869797363281, "dur": 1.120025634765625, "tid": 0, "pid": "CUDA functions", "args": {}}, {"name": "aten::resize_", "ph": "X", "ts": 289.327, "dur": 0.5219999999999914, "tid": 1, "pid": "CPU functions", "args": {}}, {"name": "aten::contiguous", "ph": "X", "ts": 290.654, "dur": 1.6829999999999927, "tid": 1, "pid": "CPU functions", "args": {}}, {"name": "aten::contiguous", "ph": "s", "ts": 290.654, "tid": 1, "pid": "CPU functions", "id": 20, "cat": "cpu_to_cuda", "args": {}}, {"name": "aten::contiguous", "ph": "f", "ts": 290.8710129394531, "tid": 0, "pid": "CUDA functions", "id": 20, "cat": "cpu_to_cuda", "args": {}}, {"name": "aten::contiguous", "ph": "X", "ts": 290.8710129394531, "dur": 0.735992431640625, "tid": 0, "pid": "CUDA functions", "args": {}}, {"name": "aten::resize_", "ph": "X", "ts": 293.553, "dur": 0.3199999999999932, "tid": 1, "pid": "CPU functions", "args": {}}, {"name": "aten::stride", "ph": "X", "ts": 295.901, "dur": 0.242999999999995, "tid": 1, "pid": "CPU functions", "args": {}}, {"name": "aten::stride", "ph": "X", "ts": 296.625, "dur": 0.20800000000002683, "tid": 1, "pid": "CPU functions", "args": {}}, {"name": "aten::stride", "ph": "X", "ts": 297.322, "dur": 0.21100000000001273, "tid": 1, "pid": "CPU functions", "args": {}}, {"name": "aten::stride", "ph": "X", "ts": 298.01, "dur": 0.21100000000001273, "tid": 1, "pid": "CPU functions", "args": {}}, {"name": "aten::empty", "ph": "X", "ts": 301.076, "dur": 0.8969999999999914, "tid": 1, "pid": "CPU functions", "args": {}}, {"name": "aten::reshape", "ph": "X", "ts": 325.894, "dur": 6.959000000000003, "tid": 1, "pid": "CPU functions", "args": {}}, {"name": "aten::reshape", "ph": "s", "ts": 325.894, "tid": 1, "pid": "CPU functions", "id": 21, "cat": "cpu_to_cuda", "args": {}}, {"name": "aten::reshape", "ph": "f", "ts": 328.47101904296875, "tid": 0, "pid": "CUDA functions", "id": 21, "cat": "cpu_to_cuda", "args": {}}, {"name": "aten::reshape", "ph": "X", "ts": 328.47101904296875, "dur": 4.447998046875, "tid": 0, "pid": "CUDA functions", "args": {}}, {"name": "aten::view", "ph": "X", "ts": 327.668, "dur": 4.341000000000008, "tid": 1, "pid": "CPU functions", "args": {}}, {"name": "aten::add_", "ph": "X", "ts": 334.92, "dur": 14.50200000000001, "tid": 1, "pid": "CPU functions", "args": {}}, {"name": "aten::add_", "ph": "s", "ts": 334.92, "tid": 1, "pid": "CPU functions", "id": 22, "cat": "cpu_to_cuda", "args": {}}, {"name": "aten::add_", "ph": "f", "ts": 334.6470139160156, "tid": 0, "pid": "CUDA functions", "id": 22, "cat": "cpu_to_cuda", "args": {}}, {"name": "aten::add_", "ph": "X", "ts": 334.6470139160156, "dur": 14.303985595703125, "tid": 0, "pid": "CUDA functions", "args": {}}, {"name": "aten::relu", "ph": "X", "ts": 366.782, "dur": 32.39699999999999, "tid": 1, "pid": "CPU functions", "args": {}}, {"name": "aten::relu", "ph": "s", "ts": 366.782, "tid": 1, "pid": "CPU functions", "id": 23, "cat": "cpu_to_cuda", "args": {}}, {"name": "aten::relu", "ph": "f", "ts": 367.38300634765625, "tid": 0, "pid": "CUDA functions", "id": 23, "cat": "cpu_to_cuda", "args": {}}, {"name": "aten::relu", "ph": "X", "ts": 367.38300634765625, "dur": 31.968017578125, "tid": 0, "pid": "CUDA functions", "args": {}}, {"name": "aten::threshold", "ph": "X", "ts": 376.195, "dur": 17.75400000000002, "tid": 1, "pid": "CPU functions", "args": {}}, {"name": "aten::threshold", "ph": "s", "ts": 376.195, "tid": 1, "pid": "CPU functions", "id": 24, "cat": "cpu_to_cuda", "args": {}}, {"name": "aten::threshold", "ph": "f", "ts": 376.5989792480469, "tid": 0, "pid": "CUDA functions", "id": 24, "cat": "cpu_to_cuda", "args": {}}, {"name": "aten::threshold", "ph": "X", "ts": 376.5989792480469, "dur": 17.600006103515625, "tid": 0, "pid": "CUDA functions", "args": {}}, {"name": "aten::empty", "ph": "X", "ts": 380.517, "dur": 5.8419999999999845, "tid": 1, "pid": "CPU functions", "args": {}}, {"name": "aten::max_pool2d", "ph": "X", "ts": 409.389, "dur": 40.49799999999999, "tid": 1, "pid": "CPU functions", "args": {}}, {"name": "aten::max_pool2d", "ph": "s", "ts": 409.389, "tid": 1, "pid": "CPU functions", "id": 25, "cat": "cpu_to_cuda", "args": {}}, {"name": "aten::max_pool2d", "ph": "f", "ts": 409.5909836425781, "tid": 0, "pid": "CUDA functions", "id": 25, "cat": "cpu_to_cuda", "args": {}}, {"name": "aten::max_pool2d", "ph": "X", "ts": 409.5909836425781, "dur": 39.7120361328125, "tid": 0, "pid": "CUDA functions", "args": {}}, {"name": "aten::max_pool2d_with_indices", "ph": "X", "ts": 411.848, "dur": 36.264999999999986, "tid": 1, "pid": "CPU functions", "args": {}}, {"name": "aten::max_pool2d_with_indices", "ph": "s", "ts": 411.848, "tid": 1, "pid": "CPU functions", "id": 26, "cat": "cpu_to_cuda", "args": {}}, {"name": "aten::max_pool2d_with_indices", "ph": "f", "ts": 414.51899267578125, "tid": 0, "pid": "CUDA functions", "id": 26, "cat": "cpu_to_cuda", "args": {}}, {"name": "aten::max_pool2d_with_indices", "ph": "X", "ts": 414.51899267578125, "dur": 33.760009765625, "tid": 0, "pid": "CUDA functions", "args": {}}, {"name": "aten::empty", "ph": "X", "ts": 421.169, "dur": 1.1440000000000055, "tid": 1, "pid": "CPU functions", "args": {}}, {"name": "aten::empty", "ph": "X", "ts": 422.966, "dur": 0.5480000000000018, "tid": 1, "pid": "CPU functions", "args": {}}, {"name": "aten::contiguous", "ph": "X", "ts": 425.8, "dur": 1.865000000000009, "tid": 1, "pid": "CPU functions", "args": {}}, {"name": "aten::contiguous", "ph": "s", "ts": 425.8, "tid": 1, "pid": "CPU functions", "id": 27, "cat": "cpu_to_cuda", "args": {}}, {"name": "aten::contiguous", "ph": "f", "ts": 425.9109909667969, "tid": 0, "pid": "CUDA functions", "id": 27, "cat": "cpu_to_cuda", "args": {}}, {"name": "aten::contiguous", "ph": "X", "ts": 425.9109909667969, "dur": 1.88800048828125, "tid": 0, "pid": "CUDA functions", "args": {}}, {"name": "aten::stride", "ph": "X", "ts": 428.996, "dur": 0.26600000000001955, "tid": 1, "pid": "CPU functions", "args": {}}, {"name": "aten::stride", "ph": "X", "ts": 429.587, "dur": 0.21000000000003638, "tid": 1, "pid": "CPU functions", "args": {}}, {"name": "aten::stride", "ph": "X", "ts": 430.114, "dur": 0.21100000000001273, "tid": 1, "pid": "CPU functions", "args": {}}, {"name": "aten::stride", "ph": "X", "ts": 430.649, "dur": 0.21300000000002228, "tid": 1, "pid": "CPU functions", "args": {}}, {"name": "aten::resize_", "ph": "X", "ts": 431.328, "dur": 3.7760000000000105, "tid": 1, "pid": "CPU functions", "args": {}}, {"name": "aten::resize_", "ph": "X", "ts": 435.541, "dur": 2.6709999999999923, "tid": 1, "pid": "CPU functions", "args": {}}, {"name": "aten::view", "ph": "X", "ts": 456.052, "dur": 4.378999999999962, "tid": 1, "pid": "CPU functions", "args": {}}, {"name": "aten::t", "ph": "X", "ts": 476.825, "dur": 6.814999999999998, "tid": 1, "pid": "CPU functions", "args": {}}, {"name": "aten::transpose", "ph": "X", "ts": 478.926, "dur": 2.5850000000000364, "tid": 1, "pid": "CPU functions", "args": {}}, {"name": "aten::as_strided", "ph": "X", "ts": 479.946, "dur": 1.186999999999955, "tid": 1, "pid": "CPU functions", "args": {}}, {"name": "aten::addmm", "ph": "X", "ts": 487.51, "dur": 65.923, "tid": 1, "pid": "CPU functions", "args": {}}, {"name": "aten::addmm", "ph": "s", "ts": 487.51, "tid": 1, "pid": "CPU functions", "id": 28, "cat": "cpu_to_cuda", "args": {}}, {"name": "aten::addmm", "ph": "f", "ts": 488.2150070800781, "tid": 0, "pid": "CUDA functions", "id": 28, "cat": "cpu_to_cuda", "args": {}}, {"name": "aten::addmm", "ph": "X", "ts": 488.2150070800781, "dur": 78.84799194335943, "tid": 0, "pid": "CUDA functions", "args": {}}, {"name": "aten::empty", "ph": "X", "ts": 495.514, "dur": 1.1309999999999718, "tid": 1, "pid": "CPU functions", "args": {}}, {"name": "aten::expand", "ph": "X", "ts": 498.276, "dur": 1.9879999999999995, "tid": 1, "pid": "CPU functions", "args": {}}, {"name": "aten::as_strided", "ph": "X", "ts": 499.265, "dur": 0.6210000000000377, "tid": 1, "pid": "CPU functions", "args": {}}, {"name": "aten::resize_", "ph": "X", "ts": 500.893, "dur": 3.768000000000029, "tid": 1, "pid": "CPU functions", "args": {}}, {"name": "aten::stride", "ph": "X", "ts": 515.16, "dur": 0.34699999999998, "tid": 1, "pid": "CPU functions", "args": {}}, {"name": "aten::stride", "ph": "X", "ts": 515.856, "dur": 0.2899999999999636, "tid": 1, "pid": "CPU functions", "args": {}}, {"name": "aten::stride", "ph": "X", "ts": 516.528, "dur": 0.21699999999998454, "tid": 1, "pid": "CPU functions", "args": {}}, {"name": "aten::relu", "ph": "X", "ts": 562.364, "dur": 24.230000000000018, "tid": 1, "pid": "CPU functions", "args": {}}, {"name": "aten::relu", "ph": "s", "ts": 562.364, "tid": 1, "pid": "CPU functions", "id": 29, "cat": "cpu_to_cuda", "args": {}}, {"name": "aten::relu", "ph": "f", "ts": 568.087046875, "tid": 0, "pid": "CUDA functions", "id": 29, "cat": "cpu_to_cuda", "args": {}}, {"name": "aten::relu", "ph": "X", "ts": 568.087046875, "dur": 18.751953125, "tid": 0, "pid": "CUDA functions", "args": {}}, {"name": "aten::threshold", "ph": "X", "ts": 568.707, "dur": 12.97199999999998, "tid": 1, "pid": "CPU functions", "args": {}}, {"name": "aten::threshold", "ph": "s", "ts": 568.707, "tid": 1, "pid": "CPU functions", "id": 30, "cat": "cpu_to_cuda", "args": {}}, {"name": "aten::threshold", "ph": "f", "ts": 570.1349594726563, "tid": 0, "pid": "CUDA functions", "id": 30, "cat": "cpu_to_cuda", "args": {}}, {"name": "aten::threshold", "ph": "X", "ts": 570.1349594726563, "dur": 12.28802490234375, "tid": 0, "pid": "CUDA functions", "args": {}}, {"name": "aten::empty", "ph": "X", "ts": 572.116, "dur": 4.162000000000035, "tid": 1, "pid": "CPU functions", "args": {}}, {"name": "aten::t", "ph": "X", "ts": 602.244, "dur": 6.706000000000017, "tid": 1, "pid": "CPU functions", "args": {}}, {"name": "aten::transpose", "ph": "X", "ts": 604.423, "dur": 2.0599999999999454, "tid": 1, "pid": "CPU functions", "args": {}}, {"name": "aten::as_strided", "ph": "X", "ts": 605.193, "dur": 0.9400000000000546, "tid": 1, "pid": "CPU functions", "args": {}}, {"name": "aten::addmm", "ph": "X", "ts": 612.276, "dur": 46.17900000000009, "tid": 1, "pid": "CPU functions", "args": {}}, {"name": "aten::addmm", "ph": "s", "ts": 612.276, "tid": 1, "pid": "CPU functions", "id": 31, "cat": "cpu_to_cuda", "args": {}}, {"name": "aten::addmm", "ph": "f", "ts": 613.1430161132813, "tid": 0, "pid": "CUDA functions", "id": 31, "cat": "cpu_to_cuda", "args": {}}, {"name": "aten::addmm", "ph": "X", "ts": 613.1430161132813, "dur": 49.1519775390625, "tid": 0, "pid": "CUDA functions", "args": {}}, {"name": "aten::empty", "ph": "X", "ts": 619.502, "dur": 1.1180000000000518, "tid": 1, "pid": "CPU functions", "args": {}}, {"name": "aten::expand", "ph": "X", "ts": 622.06, "dur": 1.6160000000000991, "tid": 1, "pid": "CPU functions", "args": {}}, {"name": "aten::as_strided", "ph": "X", "ts": 622.81, "dur": 0.54200000000003, "tid": 1, "pid": "CPU functions", "args": {}}, {"name": "aten::resize_", "ph": "X", "ts": 624.214, "dur": 4.000999999999976, "tid": 1, "pid": "CPU functions", "args": {}}, {"name": "aten::stride", "ph": "X", "ts": 636.768, "dur": 0.33299999999997, "tid": 1, "pid": "CPU functions", "args": {}}, {"name": "aten::stride", "ph": "X", "ts": 637.427, "dur": 0.2139999999999418, "tid": 1, "pid": "CPU functions", "args": {}}, {"name": "aten::stride", "ph": "X", "ts": 637.955, "dur": 0.21499999999991815, "tid": 1, "pid": "CPU functions", "args": {}}, {"name": "aten::relu", "ph": "X", "ts": 666.649, "dur": 22.663999999999987, "tid": 1, "pid": "CPU functions", "args": {}}, {"name": "aten::relu", "ph": "s", "ts": 666.649, "tid": 1, "pid": "CPU functions", "id": 32, "cat": "cpu_to_cuda", "args": {}}, {"name": "aten::relu", "ph": "f", "ts": 667.4149887695313, "tid": 0, "pid": "CUDA functions", "id": 32, "cat": "cpu_to_cuda", "args": {}}, {"name": "aten::relu", "ph": "X", "ts": 667.4149887695313, "dur": 21.95196533203125, "tid": 0, "pid": "CUDA functions", "args": {}}, {"name": "aten::threshold", "ph": "X", "ts": 672.685, "dur": 11.919000000000096, "tid": 1, "pid": "CPU functions", "args": {}}, {"name": "aten::threshold", "ph": "s", "ts": 672.685, "tid": 1, "pid": "CPU functions", "id": 33, "cat": "cpu_to_cuda", "args": {}}, {"name": "aten::threshold", "ph": "f", "ts": 672.5349838867188, "tid": 0, "pid": "CUDA functions", "id": 33, "cat": "cpu_to_cuda", "args": {}}, {"name": "aten::threshold", "ph": "X", "ts": 672.5349838867188, "dur": 12.28802490234375, "tid": 0, "pid": "CUDA functions", "args": {}}, {"name": "aten::empty", "ph": "X", "ts": 675.915, "dur": 3.7490000000000236, "tid": 1, "pid": "CPU functions", "args": {}}, {"name": "aten::t", "ph": "X", "ts": 703.282, "dur": 7.397999999999911, "tid": 1, "pid": "CPU functions", "args": {}}, {"name": "aten::transpose", "ph": "X", "ts": 705.065, "dur": 2.4329999999999927, "tid": 1, "pid": "CPU functions", "args": {}}, {"name": "aten::as_strided", "ph": "X", "ts": 705.876, "dur": 1.1200000000000045, "tid": 1, "pid": "CPU functions", "args": {}}, {"name": "aten::addmm", "ph": "X", "ts": 714.919, "dur": 56.36099999999999, "tid": 1, "pid": "CPU functions", "args": {}}, {"name": "aten::addmm", "ph": "s", "ts": 714.919, "tid": 1, "pid": "CPU functions", "id": 34, "cat": "cpu_to_cuda", "args": {}}, {"name": "aten::addmm", "ph": "f", "ts": 716.56702734375, "tid": 0, "pid": "CUDA functions", "id": 34, "cat": "cpu_to_cuda", "args": {}}, {"name": "aten::addmm", "ph": "X", "ts": 716.56702734375, "dur": 60.41595458984375, "tid": 0, "pid": "CUDA functions", "args": {}}, {"name": "aten::empty", "ph": "X", "ts": 725.083, "dur": 1.2269999999999754, "tid": 1, "pid": "CPU functions", "args": {}}, {"name": "aten::expand", "ph": "X", "ts": 727.774, "dur": 1.7889999999999873, "tid": 1, "pid": "CPU functions", "args": {}}, {"name": "aten::as_strided", "ph": "X", "ts": 728.583, "dur": 0.6610000000000582, "tid": 1, "pid": "CPU functions", "args": {}}, {"name": "aten::resize_", "ph": "X", "ts": 730.171, "dur": 3.79099999999994, "tid": 1, "pid": "CPU functions", "args": {}}, {"name": "aten::stride", "ph": "X", "ts": 742.679, "dur": 0.39800000000002456, "tid": 1, "pid": "CPU functions", "args": {}}, {"name": "aten::stride", "ph": "X", "ts": 743.419, "dur": 0.21100000000001273, "tid": 1, "pid": "CPU functions", "args": {}}, {"name": "aten::stride", "ph": "X", "ts": 743.953, "dur": 0.21199999999998909, "tid": 1, "pid": "CPU functions", "args": {}}]